{
  "query": "apple",
  "keyword_results": [],
  "country_code": "ALL",
  "results": [
    {
      "id": "100484820802",
      "category": "Product/service",
      "imageURI": "https://scontent-den2-1.xx.fbcdn.net/v/t39.30808-1/362641925_654791240027448_7555243890945175759_n.jpg?stp=dst-jpg_p200x200&_nc_cat=1&ccb=1-7&_nc_sid=2bfcec&_nc_ohc=FHb8jwwY2pMAX_fr3HP&_nc_ht=scontent-den2-1.xx&oh=00_AfA3pGLX-lrGT6ZLv-V2bh0IJJBV4hGeeFyrdTZDy4Fi7Q&oe=65A8E9E9",
      "likes": 28615907,
      "verification": "blue_verified",
      "name": "Apple TV",
      "country": null,
      "entityType": "person_profile",
      "igUsername": "appletv",
      "igFollowers": 3857712,
      "igVerification": true,
      "pageAlias": "appletv",
      "pageIsDeleted": false
    },
    {
      "id": "434174436675167",
      "category": "Product/service",
      "imageURI": "https://scontent-den2-1.xx.fbcdn.net/v/t39.30808-1/387094294_712381880925372_1615700802773976871_n.png?stp=dst-png_p200x200&_nc_cat=1&ccb=1-7&_nc_sid=2bfcec&_nc_ohc=PyquS83_q3gAX8hZ15G&_nc_ht=scontent-den2-1.xx&oh=00_AfBQ_CkapYqWAAWCgw1RkcYcNIi4S-VNFk9X-G3BcohfCA&oe=65A94AFB",
      "likes": 14233186,
      "verification": "not_verified",
      "name": "Apple",
      "country": null,
      "entityType": "person_profile",
      "igUsername": "apple",
      "igFollowers": 32083739,
      "igVerification": true,
      "pageAlias": "apple",
      "pageIsDeleted": false
    },
    {
      "id": "84917689333",
      "category": "Restaurant",
      "imageURI": "https://scontent-den2-1.xx.fbcdn.net/v/t39.30808-1/386316026_706370211523996_4097507923650436007_n.jpg?stp=dst-jpg_p200x200&_nc_cat=1&ccb=1-7&_nc_sid=2bfcec&_nc_ohc=RKiijCvkZcoAX9lAJUG&_nc_ht=scontent-den2-1.xx&oh=00_AfAaP2b0rgkZCTmVCyiaV-Ec2XSReJOhL3aos9zX-ECPIw&oe=65A91B50",
      "likes": 5858762,
      "verification": "blue_verified",
      "name": "Applebee's Grill + Bar",
      "country": null,
      "entityType": "person_profile",
      "igUsername": null,
      "igFollowers": null,
      "igVerification": null,
      "pageAlias": "applebees",
      "pageIsDeleted": false
    },
    {
      "id": "615085188507202",
      "category": "Product/service",
      "imageURI": "https://scontent-den2-1.xx.fbcdn.net/v/t39.30808-1/240242499_5225107130838295_4785253383888674944_n.jpg?stp=dst-jpg_p200x200&_nc_cat=1&ccb=1-7&_nc_sid=2bfcec&_nc_ohc=kebfVadKafYAX-0quCW&_nc_ht=scontent-den2-1.xx&oh=00_AfD6FEU6CZLN9DA1Npk1cJ5FVRuFo6Qb3MEpv_mESMLifw&oe=65A98638",
      "likes": 4285516,
      "verification": "blue_verified",
      "name": "Apple Music",
      "country": null,
      "entityType": "person_profile",
      "igUsername": "applemusic",
      "igFollowers": 4818653,
      "igVerification": true,
      "pageAlias": "applemusic",
      "pageIsDeleted": false
    },
    {
      "id": "8751461058",
      "category": "Circus",
      "imageURI": "https://scontent-den2-1.xx.fbcdn.net/v/t39.30808-1/380882637_677035584458472_8484111718257997592_n.jpg?stp=dst-jpg_p200x200&_nc_cat=108&ccb=1-7&_nc_sid=2bfcec&_nc_ohc=syghda8zdEAAX9XcLKp&_nc_ht=scontent-den2-1.xx&oh=00_AfCafHYeLDTkegVj4tVBAQim3c74y4yTmvHQI1A-4tMsqg&oe=65A9EC51",
      "likes": 62400,
      "verification": "blue_verified",
      "name": "Big Apple Circus",
      "country": null,
      "entityType": "person_profile",
      "igUsername": "bigapplecircus",
      "igFollowers": 28381,
      "igVerification": true,
      "pageAlias": "bigapplecircus",
      "pageIsDeleted": false
    },
    {
      "id": "232633627068",
      "category": "Media/News Company",
      "imageURI": "https://scontent-den2-1.xx.fbcdn.net/v/t39.30808-1/347811115_964189035030447_7088575326582513018_n.png?stp=dst-png_p200x200&_nc_cat=102&ccb=1-7&_nc_sid=2bfcec&_nc_ohc=pPo2AytaYJ4AX9AA2bz&_nc_ht=scontent-den2-1.xx&oh=00_AfD5QJX536u3EY9RAINc1C3LWUKJMhtG-07mHG5Oq_4CyA&oe=65A8D186",
      "likes": 3717722,
      "verification": "blue_verified",
      "name": "蘋果新聞網",
      "country": null,
      "entityType": "person_profile",
      "igUsername": "appledailytw",
      "igFollowers": 271604,
      "igVerification": true,
      "pageAlias": "appledaily.tw",
      "pageIsDeleted": false
    },
    {
      "id": "334500153341766",
      "category": "Business Service",
      "imageURI": "https://scontent-den2-1.xx.fbcdn.net/v/t39.30808-1/352525985_176428158445770_6198811735597772354_n.jpg?stp=dst-jpg_p200x200&_nc_cat=108&ccb=1-7&_nc_sid=2bfcec&_nc_ohc=Rnc82TZx-eIAX-M7BwV&_nc_ht=scontent-den2-1.xx&oh=00_AfBa8SeQFjOZBuUYwuICvdGilXdYQO3r6v9aWVnSq4sDlQ&oe=65A9D80F",
      "likes": 1511462,
      "verification": "blue_verified",
      "name": "ABM (Apple Authorised Distributor)",
      "country": null,
      "entityType": "person_profile",
      "igUsername": "abmmiddleeast",
      "igFollowers": 8350,
      "igVerification": false,
      "pageAlias": "ABM.AppleAuthoriseDistributor",
      "pageIsDeleted": false
    },
    {
      "id": "65962293904",
      "category": "Travel agency",
      "imageURI": "https://scontent-den2-1.xx.fbcdn.net/v/t39.30808-1/271447206_10159543071298905_1499986390802828436_n.jpg?stp=dst-jpg_p200x200&_nc_cat=1&ccb=1-7&_nc_sid=2bfcec&_nc_ohc=-2WNf30FhIkAX_mfeCQ&_nc_ht=scontent-den2-1.xx&oh=00_AfBaxBUM3sLoQVug5hV_eFhkuN2TRt1CpClD2Cyp3I-SkA&oe=65A9CB89",
      "likes": 256827,
      "verification": "not_verified",
      "name": "Apple Vacations",
      "country": null,
      "entityType": "person_profile",
      "igUsername": "applevacations",
      "igFollowers": 45127,
      "igVerification": false,
      "pageAlias": "applevacations",
      "pageIsDeleted": false
    },
    {
      "id": "718559314911006",
      "category": "Computer Store",
      "imageURI": "https://scontent-den2-1.xx.fbcdn.net/v/t39.30808-1/240593606_235999378541460_8363845409510997115_n.jpg?stp=dst-jpg_p200x200&_nc_cat=103&ccb=1-7&_nc_sid=2bfcec&_nc_ohc=8Ql7lYad3RoAX-6swF_&_nc_ht=scontent-den2-1.xx&oh=00_AfAFJ3Eh5ydpqQpdwwUOwPlsYZ98l6lyspKZo0epnONUDw&oe=65A9CE34",
      "likes": 5456,
      "verification": "not_verified",
      "name": "Apple",
      "country": null,
      "entityType": "person_profile",
      "igUsername": null,
      "igFollowers": null,
      "igVerification": null,
      "pageAlias": "dailyvideodose53",
      "pageIsDeleted": false
    },
    {
      "id": "2011105812436774",
      "category": "Travel Company",
      "imageURI": "https://scontent-den2-1.xx.fbcdn.net/v/t39.30808-1/327208130_872328507422638_7578508438740995521_n.png?stp=dst-png_p200x200&_nc_cat=111&ccb=1-7&_nc_sid=2bfcec&_nc_ohc=Ipyp52FzFoMAX_UovxC&_nc_ht=scontent-den2-1.xx&oh=00_AfAirYWKlND_J8C6kxU2NFb4sq7dZjWdskPc3i-4KxZvSA&oe=65A81978",
      "likes": 104240,
      "verification": "not_verified",
      "name": "Apple Vacations",
      "country": null,
      "entityType": "person_profile",
      "igUsername": "applevacationsmy",
      "igFollowers": 8287,
      "igVerification": false,
      "pageAlias": "applevacationsmy",
      "pageIsDeleted": false
    },
    {
      "id": "158285920894235",
      "category": "Computer Store",
      "imageURI": "https://scontent-den2-1.xx.fbcdn.net/v/t39.30808-1/325346758_1199734094005507_7046115456378948387_n.png?_nc_cat=103&ccb=1-7&_nc_sid=2bfcec&_nc_ohc=Uq1VTfOUIYIAX8X9SQ2&_nc_ht=scontent-den2-1.xx&oh=00_AfDNIMGUxDHfqDYMC1WQzjD0Z2iUrClRwqUloKbebGoxpQ&oe=65A95F37",
      "likes": 74007,
      "verification": "not_verified",
      "name": "iSpot Apple Premium Partner",
      "country": null,
      "entityType": "person_profile",
      "igUsername": "ispotpl",
      "igFollowers": 32040,
      "igVerification": false,
      "pageAlias": "iSpotpl",
      "pageIsDeleted": false
    },
    {
      "id": "105736048547",
      "category": "Food & Beverage",
      "imageURI": "https://scontent-den2-1.xx.fbcdn.net/v/t39.30808-1/312230609_10160036758353548_4874876838755790906_n.jpg?stp=dst-jpg_p200x200&_nc_cat=105&ccb=1-7&_nc_sid=2bfcec&_nc_ohc=2Mv1Q3MPjugAX9uisc4&_nc_ht=scontent-den2-1.xx&oh=00_AfAPRqQb62R5_VVDLh_lnEDK9XZB3cYPJVTi2gjthONnVg&oe=65A99DCB",
      "likes": 1254079,
      "verification": "blue_verified",
      "name": "Applegate",
      "country": null,
      "entityType": "person_profile",
      "igUsername": "applegate",
      "igFollowers": 76019,
      "igVerification": true,
      "pageAlias": "applegate",
      "pageIsDeleted": false
    },
    {
      "id": "792822820734693",
      "category": "Phone/Tablet",
      "imageURI": "https://scontent-den2-1.xx.fbcdn.net/v/t1.30497-1/143086968_2856368904622192_1959732218791162458_n.png?_nc_cat=1&ccb=1-7&_nc_sid=810bd0&_nc_ohc=nZwDo3Nj-b8AX8Pliwo&_nc_ht=scontent-den2-1.xx&oh=00_AfAU3kYIfyOe8y-N7yAuNIk570S5waNZ6V8WVocXHc5pAQ&oe=65CB82F8",
      "likes": 39148,
      "verification": "not_verified",
      "name": "Apple",
      "country": null,
      "entityType": "person_profile",
      "igUsername": null,
      "igFollowers": null,
      "igVerification": null,
      "pageAlias": "Ns.Apple1",
      "pageIsDeleted": false
    },
    {
      "id": "235610666602317",
      "category": "Community",
      "imageURI": "https://scontent-den2-1.xx.fbcdn.net/v/t39.30808-1/306995042_440002638220913_2770206877356599795_n.jpg?stp=dst-jpg_p200x200&_nc_cat=102&ccb=1-7&_nc_sid=2bfcec&_nc_ohc=qeq-YKQB4zcAX-SkHSK&_nc_ht=scontent-den2-1.xx&oh=00_AfBjPU3JlVbPiiQ8cQGcDFVxaLVj7EFeOFQhpUnUJZH1Qw&oe=65A81EE7",
      "likes": 34393,
      "verification": "not_verified",
      "name": "Apple",
      "country": null,
      "entityType": "person_profile",
      "igUsername": null,
      "igFollowers": null,
      "igVerification": null,
      "pageAlias": "Apple.Strike1999",
      "pageIsDeleted": false
    },
    {
      "id": "527051050660867",
      "category": "Community",
      "imageURI": "https://scontent-den2-1.xx.fbcdn.net/v/t39.30808-1/307309881_203105225399318_7846497259588250980_n.jpg?stp=dst-jpg_p200x200&_nc_cat=106&ccb=1-7&_nc_sid=2bfcec&_nc_ohc=dvMUAM7zfCMAX9lGU_L&_nc_ht=scontent-den2-1.xx&oh=00_AfBZTtp9Xlz0KB5kIZg-3LPi0L4uixj0c__KJNXBrcODmA&oe=65A86D1D",
      "likes": 19901,
      "verification": "not_verified",
      "name": "Apple.",
      "country": null,
      "entityType": "person_profile",
      "igUsername": null,
      "igFollowers": null,
      "igVerification": null,
      "pageAlias": "AppleFortnite",
      "pageIsDeleted": false
    }
  ]
}